demuxes/probador.v
module probador(

    output reg clk, // clk

    output reg [5:0] data_in, // entrada de datos
 
    output reg reset_L, // reset_L para correcto funcionamiento estructural

    output reg valid_in, // valid de entrada

    // -------------> Estructural <---------------------

    output reg [31:0] data_in_estr, // entrada de datos


    output reg valid_in_estr // valid de entrada
    
    );

    initial begin

    $dumpfile("./dump/demux_vcid.vcd");
    $dumpvars;

    data_in <= 0;
    valid_in <= 0;
    reset_L <= 0;

    @(posedge clk);
    @(posedge clk);

    data_in <= 6'b01_0001;
    reset_L <= 1;
    valid_in <= 1;
    @(posedge clk);

    data_in <= 6'b11_0010;
    @(posedge clk);

    data_in <= 6'b11_0011;
    @(posedge clk);

    data_in <= 6'b01_0100;
    @(posedge clk);

    data_in <= 0;
    valid_in <= 0;
    @(posedge clk);


    @(posedge clk);
    @(posedge clk);

    $finish;
    end

    initial clk <= 0;
    always #2 clk <= ~clk;

endmodule

demux_vcid/demux_vc_id.v
module demux_vc_id #(  
                            parameter BW = 6
)

                        (   input clk,
                            input reset_L,
                            output reg [BW-1:0] data_in_vc0,
                            output reg valid_in_vc0,
                            output reg[BW-1:0] data_in_vc1,
                            output reg valid_in_vc1,
                            input valid_in,
                            input [BW-1:0] data_in
                        );

                        
    reg [BW-1:0] data_recordar0;
    reg [BW-1:0] data_recordar1;
    reg valid_recordar0;
    reg valid_recordar1;

    wire selector;
    assign selector = data_in[5];

    always @(*) begin   
        if (selector == 0 && valid_in == 1) begin
            data_recordar0 = data_in;
            data_recordar1 = 0;
            valid_recordar0 = valid_in;
            valid_recordar1 = 0;


        end else if (selector == 1 && valid_in == 1) begin
            data_recordar0 = 0;
            data_recordar1 = data_in;
            valid_recordar0 = 0;
            valid_recordar1 = valid_in;

        end else begin
            data_recordar0 = 0;
            data_recordar1 = 0;
            valid_recordar0 = 0;
            valid_recordar1 = 0;
        end
    end

    always @(posedge clk) begin
        if (reset_L == 1) begin
            if (selector == 0) begin
                data_in_vc0 <= data_recordar0;
                valid_in_vc0 <= valid_recordar0;
                valid_in_vc1 <= 0; //para evitar falsos pushes
            end else if (selector == 1) begin
                data_in_vc1 <= data_recordar1;
                valid_in_vc1 <= valid_recordar1;
                valid_in_vc0 <= 0; //para evitar falsos pushes
            end
        end else begin
            data_in_vc0 <= 0;
            data_in_vc1 <= 0;
            valid_in_vc0 <= 0;
            valid_in_vc1 <= 0;
        end
    end

endmodule

demuxes/testbench.v
`timescale 1ns/100ps

`include "probador.v"

`include "demux_vc_id.v"

module testbench;

    //PARAMS
    parameter BW=6;

    /*AUTOWIRE*/
    // Beginning of automatic wires (for undeclared instantiated-module outputs)
    wire		clk;			// From prb of probador.v
    wire [5:0]		data_in;		// From prb of probador.v
    wire [31:0]		data_in_estr;		// From prb of probador.v
    wire [BW-1:0]	data_in_vc0;		// From d_vc_id of demux_vc_id.v
    wire [BW-1:0]	data_in_vc1;		// From d_vc_id of demux_vc_id.v
    wire		reset_L;		// From prb of probador.v
    wire		valid_in;		// From prb of probador.v
    wire		valid_in_estr;		// From prb of probador.v
    wire		valid_in_vc0;		// From d_vc_id of demux_vc_id.v
    wire		valid_in_vc1;		// From d_vc_id of demux_vc_id.v
    // End of automatics

    demux_vc_id d_vc_id (/*AUTOINST*/
			 // Outputs
			 .data_in_vc0		(data_in_vc0[BW-1:0]),
			 .valid_in_vc0		(valid_in_vc0),
			 .data_in_vc1		(data_in_vc1[BW-1:0]),
			 .valid_in_vc1		(valid_in_vc1),
			 // Inputs
			 .clk			(clk),
			 .reset_L		(reset_L),
			 .valid_in		(valid_in),
			 .data_in		(data_in[BW-1:0]));

    probador prb (/*AUTOINST*/
		  // Outputs
		  .clk			(clk),
		  .data_in		(data_in[5:0]),
		  .reset_L		(reset_L),
		  .valid_in		(valid_in),
		  .data_in_estr		(data_in_estr[31:0]),
		  .valid_in_estr	(valid_in_estr));

endmodule

demuxes/dump/demux_vcid.vcd
$date
	Tue Nov  3 16:56:14 2020
$end
$version
	Icarus Verilog
$end
$timescale
	100ps
$end
$scope module testbench $end
$var wire 1 ! valid_in_vc1 $end
$var wire 1 " valid_in_vc0 $end
$var wire 1 # valid_in_estr $end
$var wire 1 $ valid_in $end
$var wire 1 % reset_L $end
$var wire 6 & data_in_vc1 [5:0] $end
$var wire 6 ' data_in_vc0 [5:0] $end
$var wire 32 ( data_in_estr [31:0] $end
$var wire 6 ) data_in [5:0] $end
$var wire 1 * clk $end
$scope module d_vc_id $end
$var wire 1 $ valid_in $end
$var wire 1 + selector $end
$var wire 1 % reset_L $end
$var wire 6 , data_in [5:0] $end
$var wire 1 * clk $end
$var reg 6 - data_in_vc0 [5:0] $end
$var reg 6 . data_in_vc1 [5:0] $end
$var reg 6 / data_recordar0 [5:0] $end
$var reg 6 0 data_recordar1 [5:0] $end
$var reg 1 " valid_in_vc0 $end
$var reg 1 ! valid_in_vc1 $end
$var reg 1 1 valid_recordar0 $end
$var reg 1 2 valid_recordar1 $end
$upscope $end
$scope module prb $end
$var reg 1 * clk $end
$var reg 6 3 data_in [5:0] $end
$var reg 32 4 data_in_estr [31:0] $end
$var reg 1 % reset_L $end
$var reg 1 $ valid_in $end
$var reg 1 # valid_in_estr $end
$upscope $end
$upscope $end
$enddefinitions $end
#0
$dumpvars
bx 4
b0 3
02
01
b0 0
b0 /
bx .
bx -
b0 ,
0+
0*
b0 )
bx (
bx '
bx &
0%
0$
x#
x"
x!
$end
#20
0!
0"
b0 &
b0 .
b0 '
b0 -
1*
#40
0*
#60
11
b10001 /
1$
1%
b10001 )
b10001 ,
b10001 3
1*
#80
0*
#100
12
01
b110010 0
1+
b0 /
1"
b10001 '
b10001 -
b110010 )
b110010 ,
b110010 3
1*
#120
0*
#140
b110011 0
b110011 )
b110011 ,
b110011 3
0"
1!
b110010 &
b110010 .
1*
#160
0*
#180
02
11
b10100 /
0+
b0 0
b110011 &
b110011 .
b10100 )
b10100 ,
b10100 3
1*
#200
0*
#220
01
b0 /
0$
b0 )
b0 ,
b0 3
0!
1"
b10100 '
b10100 -
1*
#240
0*
#260
0"
b0 '
b0 -
1*
