pop_delay_vc0/probador.v
module probador(

    output reg clk,

    output reg reset_L,

    output reg d0_full,

    output reg d1_full,

    output reg vc0_empty,

    output reg vc1_empty

    // -------> Estructurales --------->


    );

    initial begin

    $dumpfile("./dump/pop_delay_vc0.vcd");
    $dumpvars;

    reset_L <= 0;

    d0_full <= 0;
    d1_full <= 0;
    vc0_empty <= 1;
    vc1_empty <= 1;
    @(posedge clk);

    // pop vc0
    reset_L <= 1;

    d0_full <= 0;
    d1_full <= 0;
    vc0_empty <= 0;
    vc1_empty <= 0;
    @(posedge clk);

    // no pop vc0
    d0_full <= 1;
    d1_full <= 1;
    vc0_empty <= 0;
    vc1_empty <= 0;
    @(posedge clk);

    // no pop vc0
    d0_full <= 0;
    d1_full <= 0;
    vc0_empty <= 1;
    vc1_empty <= 1;
    @(posedge clk);

    // no pop vc0
    d0_full <= 1;
    d1_full <= 1;
    vc0_empty <= 1;
    vc1_empty <= 1;
    @(posedge clk);

    // pop vc0
    d0_full <= 0;
    d1_full <= 0;
    vc0_empty <= 0;
    vc1_empty <= 0;
    @(posedge clk);

    // no pop vc0
    d0_full <= 0;
    d1_full <= 0;
    vc0_empty <= 1;
    vc1_empty <= 0;
    @(posedge clk);
    @(posedge clk);

    $finish;
    end

    initial clk <= 0;
    always #2 clk <= ~clk;


endmodule

pop_delay_vc0/pop_delay_vc0.v
module pop_delay_vc0(
    input clk,
    input reset_L,
    input d0_full,
    input d1_full,
    input vc0_empty,
    input vc1_empty,
    output reg vc0_delay,
    output reg vc0_read,
    output reg vc1_read
);

    reg and_d0d1;
    reg and_vc0_0;
    reg and_vc0_1;
    reg vc0_delay_recordar;
    reg vc0_read_recordar;
    reg vc1_read_recordar;
    
    // and de d0 y d1
    always @(*) begin
        if (d0_full && d1_full) begin
            and_d0d1 = 1;
        end else begin
            and_d0d1 = 0;
        end
    end

    // and final 0
    always @(*) begin
        if (!(vc0_empty) && !(and_d0d1)) begin
            and_vc0_0 = 1;
        end else begin
            and_vc0_0 = 0;
        end
    end

    // and final 1
    always @(*) begin
        if (vc0_empty && !(and_d0d1) && !(vc1_empty)) begin
            and_vc0_1 = 1;
        end else begin
            and_vc0_1 = 0;
        end
    end

    // pop delay
    always @(*) begin
        if (and_vc0_0 == 1) begin
            vc0_delay_recordar = 0;
            vc0_read_recordar = 1;
            vc1_read_recordar = 0;
        end 
        else if (and_vc0_1 && !(and_vc0_0)) begin
            vc0_delay_recordar = 1;
            vc0_read_recordar = 0;
            vc1_read_recordar = 1;
        end else begin
            vc0_delay_recordar = 0;
            vc0_read_recordar = 0;
            vc1_read_recordar = 0;
        end
    end

    // pop delay flop
    always @(posedge clk) begin
        if (reset_L == 1) begin
            if (and_vc0_0 == 1) begin
                vc0_delay <= vc0_delay_recordar;
                vc0_read <= vc0_read_recordar;
                vc1_read <= vc1_read_recordar;
            end 
            else if (and_vc0_1 && !(and_vc0_0)) begin
                vc0_delay <= vc0_delay_recordar;
                vc0_read <= vc0_read_recordar;
                vc1_read <= vc1_read_recordar;
            end else begin
                vc0_delay <= 0;
                vc0_read <= 0;
                vc1_read <= 0;
            end
        end else begin
            vc0_delay <= 0;
            vc0_read <= 0;
            vc1_read <= 0;
        end
    end

endmodule

pop_delay_vc0/testbench.v
`timescale 1ns/100ps

`include "probador.v"

`include "pop_delay_vc0.v"

module testbench;

    /*AUTOWIRE*/
    // Beginning of automatic wires (for undeclared instantiated-module outputs)
    wire		clk;			// From prb of probador.v
    wire		d0_full;		// From prb of probador.v
    wire		d1_full;		// From prb of probador.v
    wire		reset_L;		// From prb of probador.v
    wire		vc0_delay;		// From pop_vc0 of pop_delay_vc0.v
    wire		vc0_empty;		// From prb of probador.v
    wire		vc0_read;		// From pop_vc0 of pop_delay_vc0.v
    wire		vc1_empty;		// From prb of probador.v
    wire		vc1_read;		// From pop_vc0 of pop_delay_vc0.v
    // End of automatics

    pop_delay_vc0 pop_vc0 (/*AUTOINST*/
			   // Outputs
			   .vc0_delay		(vc0_delay),
			   .vc0_read		(vc0_read),
			   .vc1_read		(vc1_read),
			   // Inputs
			   .clk			(clk),
			   .reset_L		(reset_L),
			   .d0_full		(d0_full),
			   .d1_full		(d1_full),
			   .vc0_empty		(vc0_empty),
			   .vc1_empty		(vc1_empty));


    probador prb (/*AUTOINST*/
		  // Outputs
		  .clk			(clk),
		  .reset_L		(reset_L),
		  .d0_full		(d0_full),
		  .d1_full		(d1_full),
		  .vc0_empty		(vc0_empty),
		  .vc1_empty		(vc1_empty));

endmodule

pop_delay_vc0/dump/pop_delay_vc0.vcd
$date
	Wed Nov  4 14:41:22 2020
$end
$version
	Icarus Verilog
$end
$timescale
	100ps
$end
$scope module testbench $end
$var wire 1 ! vc1_read $end
$var wire 1 " vc1_empty $end
$var wire 1 # vc0_read $end
$var wire 1 $ vc0_empty $end
$var wire 1 % vc0_delay $end
$var wire 1 & reset_L $end
$var wire 1 ' d1_full $end
$var wire 1 ( d0_full $end
$var wire 1 ) clk $end
$scope module pop_vc0 $end
$var wire 1 " vc1_empty $end
$var wire 1 $ vc0_empty $end
$var wire 1 & reset_L $end
$var wire 1 ' d1_full $end
$var wire 1 ( d0_full $end
$var wire 1 ) clk $end
$var reg 1 * and_d0d1 $end
$var reg 1 + and_vc0_0 $end
$var reg 1 , and_vc0_1 $end
$var reg 1 % vc0_delay $end
$var reg 1 - vc0_delay_recordar $end
$var reg 1 # vc0_read $end
$var reg 1 . vc0_read_recordar $end
$var reg 1 ! vc1_read $end
$var reg 1 / vc1_read_recordar $end
$upscope $end
$scope module prb $end
$var reg 1 ) clk $end
$var reg 1 ( d0_full $end
$var reg 1 ' d1_full $end
$var reg 1 & reset_L $end
$var reg 1 $ vc0_empty $end
$var reg 1 " vc1_empty $end
$upscope $end
$upscope $end
$enddefinitions $end
#0
$dumpvars
0/
0.
0-
0,
0+
0*
0)
0(
0'
0&
x%
1$
x#
1"
x!
$end
#20
1.
1+
0!
0#
0%
0"
0$
1&
1)
#40
0)
#60
0.
0+
1*
1'
1(
1#
1)
#80
0)
#100
0*
0#
1"
1$
0'
0(
1)
#120
0)
#140
1*
1'
1(
1)
#160
0)
#180
1.
1+
0*
0"
0$
0'
0(
1)
#200
0)
#220
1/
0.
1-
1,
0+
1$
1#
1)
#240
0)
#260
1!
0#
1%
1)
